Alternative/__init__.py
Alternative/alternative.py
Examples/__init__.py
Graphs/__init__.py
Graphs/credal_ranking.py
Graphs/graph.py
Models/MCDMProblem.py
Models/__init__.py
Models/AHP/GaussianAHP.py
Models/AHP/IntervalAHP.py
Models/AHP/StandardAHP.py
Models/AHP/TriangularAHP.py
Models/AHP/__init__.py
Models/BWM/BetaBWM.py
Models/BWM/GaussianBWM.py
Models/BWM/IntervalBWM.py
Models/BWM/MultinomialBWM.py
Models/BWM/StandardBWM.py
Models/BWM/TriangularBWM.py
Models/BWM/__init__.py
Models/SWING/GaussianSWING.py
Models/SWING/IntervalSWING.py
Models/SWING/StandardSWING.py
Models/SWING/TriangularSWING.py
Models/SWING/__init__.py
Models/WeightAnalyzer/StandardWeightAnalyzer.py
Models/WeightAnalyzer/WeightAnalyzerSWING.py
Models/WeightAnalyzer/__init__.py
bayesnmcdm-0.1.0.dist-info/METADATA
bayesnmcdm-0.1.0.dist-info/WHEEL
bayesnmcdm-0.1.0.dist-info/top_level.txt
bayesnmcdm-0.1.0.dist-info/RECORD
