Metadata-Version: 2.4
Name: bayesnmcdm
Version: 0.1.0
Summary: Bayesian Multi-Criteria Decision Making Toolkit
Author: Majid Mohammadi
Requires-Dist: numpy
Requires-Dist: pystan
Dynamic: author
Dynamic: requires-dist
Dynamic: summary
